koalak/__init__.py
koalak/consts.py
koalak/config/__init__.py
koalak/config/config.py
koalak/containers/__init__.py
koalak/containers/functions.py
koalak/containers/generic_container.py
koalak/containers/utils.py
koalak/descriptions/__init__.py
koalak/descriptions/entity_description.py
koalak/descriptions/field_description.py
koalak/descriptions/schema_description.py
koalak/plugin_manager/__init__.py
koalak/plugin_manager/base_plugin.py
koalak/plugin_manager/constraints.py
koalak/plugin_manager/consts.py
koalak/plugin_manager/packages_distributions_utils.py
koalak/plugin_manager/plugin_manager.py
koalak/plugin_manager/plugin_metadata.py
koalak/plugin_manager/utils.py
koalak/subcommand_parser/__init__.py
koalak/subcommand_parser/subcommand_parser.py
koalak/subcommand_parser/subcommand_printer.py
koalak/utils/__init__.py
koalak/utils/decorators.py
koalak/utils/utils.py
koalak-0.4.2.dist-info/licenses/LICENSE
koalak-0.4.2.dist-info/METADATA
koalak-0.4.2.dist-info/WHEEL
koalak-0.4.2.dist-info/top_level.txt
koalak-0.4.2.dist-info/RECORD
