Metadata-Version: 2.4
Name: koalak
Version: 0.4.2
Summary: Library designed to simplify the development of applications with a plugin-based architecture.
Author-email: Nazime LAKEHAL <nazime.lkh@gmail.com>
License:                                  Apache License
Requires-Python: >=3.7
License-File: LICENSE
Requires-Dist: attrs
Requires-Dist: argcomplete
Requires-Dist: toml
Requires-Dist: typeguard>=4
Requires-Dist: rich
Requires-Dist: devtools
Requires-Dist: pyyaml
Requires-Dist: openpyxl
Requires-Dist: deepmerge
Provides-Extra: docs
Requires-Dist: mkdocs; extra == "docs"
Requires-Dist: mkdocs-material; extra == "docs"
Requires-Dist: mkdocs-plugin-progress; extra == "docs"
Requires-Dist: mkdocs-tooltips; extra == "docs"
Requires-Dist: mkdocs-minify-plugin; extra == "docs"
Requires-Dist: mkdocs-git-revision-date-localized-plugin; extra == "docs"
Requires-Dist: mkdocs-glightbox; extra == "docs"
Requires-Dist: mkdocs-awesome-pages-plugin; extra == "docs"
Provides-Extra: tests
Requires-Dist: coverage; extra == "tests"
Requires-Dist: pytest>=4.3.0; extra == "tests"
Requires-Dist: coloring; extra == "tests"
Provides-Extra: dev
Requires-Dist: koalak; extra == "dev"
Requires-Dist: koalak[tests]; extra == "dev"
Dynamic: license-file
